cfengine_cli/__init__.py
cfengine_cli/__main__.py
cfengine_cli/commands.py
cfengine_cli/deptool-README.md
cfengine_cli/deptool.py
cfengine_cli/dev.py
cfengine_cli/docs.py
cfengine_cli/format.py
cfengine_cli/lint.py
cfengine_cli/main.py
cfengine_cli/paths.py
cfengine_cli/profile.py
cfengine_cli/shell.py
cfengine_cli/utils.py
cfengine_cli/version.py
cfengine_cli/masterfiles/__init__.py
cfengine_cli/masterfiles/analyze.py
cfengine_cli/masterfiles/check_download_matches_git.py
cfengine_cli/masterfiles/download.py
cfengine_cli/masterfiles/generate_release_information.py
cfengine_cli/masterfiles/generate_vcf_download.py
cfengine_cli/masterfiles/generate_vcf_git_checkout.py
cfengine-0.10.1.dist-info/METADATA
cfengine-0.10.1.dist-info/WHEEL
cfengine-0.10.1.dist-info/entry_points.txt
cfengine-0.10.1.dist-info/top_level.txt
cfengine-0.10.1.dist-info/RECORD
