Metadata-Version: 2.4
Name: cfengine
Version: 0.10.1
Summary: Human-oriented CLI for interacting with CFEngine tools
License:                     GNU GENERAL PUBLIC LICENSE
Classifier: Development Status :: 3 - Alpha
Classifier: Intended Audience :: Developers
Classifier: Intended Audience :: System Administrators
Classifier: Intended Audience :: Information Technology
Classifier: Topic :: Security
Classifier: Topic :: Software Development :: Build Tools
Classifier: Topic :: System :: Distributed Computing
Classifier: Topic :: System :: Systems Administration
Classifier: Programming Language :: Python :: 3
Classifier: Programming Language :: Python :: 3.9
Classifier: Programming Language :: Python :: 3.10
Classifier: Programming Language :: Python :: 3.11
Classifier: Programming Language :: Python :: 3.12
Classifier: Programming Language :: Python :: 3.13
Classifier: License :: OSI Approved :: GNU General Public License v3 (GPLv3)
Requires-Python: >=3.10
Requires-Dist: cf-remote>=0.7.3
Requires-Dist: cfbs>=5.5.0
Requires-Dist: tree-sitter-cfengine>=1.0.12
Requires-Dist: tree-sitter>=0.25
Requires-Dist: markdown-it-py>=3.0.0
